siNLP/__init__.py
siNLP/text_summary.py
siNLP/sentence_generation/__init__.py
siNLP/sentence_generation/main.py
siNLP/sentence_generation/models/Ngram.py
siNLP/sentence_generation/models/__init__.py
siNLP/sentence_generation/sentence/SentenceGenerator.py
siNLP/sentence_generation/sentence/__init__.py
siNLP/simple_algorithms/__init__.py
siNLP/simple_algorithms/tagging.py
siNLP/simple_tasks/__init__.py
siNLP/simple_tasks/palindrom.py
siNLP/tokenization/__init__.py
siNLP/tokenization/gram.py
siNLP/tokenization/prepocessing.py
SiNLP-0.0.2.dist-info/LICENSE
SiNLP-0.0.2.dist-info/METADATA
SiNLP-0.0.2.dist-info/WHEEL
SiNLP-0.0.2.dist-info/top_level.txt
SiNLP-0.0.2.dist-info/RECORD
