Metadata-Version: 2.1
Name: SiNLP
Version: 0.0.2
Summary: A library that implements NLP tasks in a simple manner.
Home-page: https://github.com/christopher-chandler/SiNLP
Author: Christopher Chandler
Author-email: christopher.chandler @outlook.de
License: MIT
Platform: UNKNOWN
License-File: LICENSE
